ml/__init__.py
ml/baryclust/BC_Clust.py
ml/baryclust/StreamBarycentric.py
ml/baryclust/__init__.py
ml/densityclust/DS2L_SOM.py
ml/densityclust/__init__.py
test/__init__.py
test/baryclust/__init__.py
test/baryclust/test_BC_Clust.py
test/baryclust/test_StreamBarycentric.py
test/densityclust/__init__.py
test/densityclust/test_DS2L_SOM.py
test/unsupervised/__init__.py
test/unsupervised/test_BC_Clust.py
test/unsupervised/test_DS2L_SOM.py
test/unsupervised2/__init__.py
test/unsupervised2/test_StreamBarycentric.py
univlabo_Talibe-1.1.1.dist-info/LICENSE
univlabo_Talibe-1.1.1.dist-info/METADATA
univlabo_Talibe-1.1.1.dist-info/WHEEL
univlabo_Talibe-1.1.1.dist-info/top_level.txt
univlabo_Talibe-1.1.1.dist-info/RECORD
