Metadata-Version: 2.1
Name: univlabo-Talibe
Version: 1.1.1
Summary: A LIBRAIRY
Home-page: https://github.com/SokhnaNdate/univlabo
Author: Ndate SOW
Author-email: ndatesowthioune@gmail.com
License: UNKNOWN
Platform: UNKNOWN
Classifier: Programming Language :: Python :: 3
Classifier: License :: OSI Approved :: MIT License
Classifier: Operating System :: OS Independent
Requires-Python: >=3.6
